appupup
