Metadata-Version: 2.1
Name: appupup
Version: 0.3.0
Summary: A peer to peer, zmq based network library.
Home-page: https://github.com/pyl1b/appupup
Author: Nicu Tofan
Author-email: nicu.tofan@gmail.com
License: MIT
Download-URL: https://github.com/pyl1b/appupup/archive/v0.3.0.zip
Project-URL: Bug Tracker, https://github.com/pyl1b/appupup/issues
Project-URL: Documentation, https://readthedocs.org/projects/appupup/
Project-URL: Source Code, https://github.com/pyl1b/appupup
Platform: UNKNOWN
Classifier: Development Status :: 3 - Alpha
Classifier: Intended Audience :: Developers
Classifier: License :: OSI Approved :: MIT License
Classifier: Programming Language :: Python
Classifier: Programming Language :: Python :: 3
Classifier: Programming Language :: Python :: 3.6
Classifier: Programming Language :: Python :: Implementation :: CPython
Classifier: Programming Language :: Python :: Implementation :: PyPy
Requires-Python: >=3.6.0
Provides-Extra: dev
Provides-Extra: tests
